{"hackathon-description-text": "\nCalling Austin software developers!", "hackathon-number-of-prizes": "4", "hackathon-id": "hackingeast", "hackathon-judges": [{"judge-role": "CEO at Gluu", "judge-name": "Mike Schwartz"}, {"judge-role": "Senior Interaction Designer at Ebay", "judge-name": "John Goff"}, {"judge-role": "Senior Software Engineer at HP Cloud Services", "judge-name": "Jeff Kramer"}, {"judge-role": "President at YellowFin Strategy + Design, E.A.S.T. Artist", "judge-name": "Tina Schweiger"}], "hackathon-number-of-judges": "4", "hackathon-eligibility": "\nAll are welcome and eligible to participate in this challenge.", "hackathon-number-of-participants": "45", "hackathon-is-colocated": "True", "hackathon-has-ended": "True", "hackathon-number-of-judging-criteria": "3", "hackathon-requirements": "\nAll app submissions should follow these requirements:", "hackathon-rules": "", "hackathon-prizes": [{"prize-content": "Winning team members will each receive a SXSW Interactive Badge (up to four total.)", "prize-title": "SXSW Interactive Badge"}, {"prize-content": "Runner-ups will receive their choice of paintings donated by local Austin artists.", "prize-title": "Art from local Austin artists"}, {"prize-content": "BigMedium has offered four tickets to their fundraiser at the WEST Group Show opening and catalog premiere. Food, drinks, music and art galore!", "prize-title": "DUE WEST!"}, {"prize-content": "One month of dedicated work space in the GoLab Gallery located in downtown Austin, TX.", "prize-title": "1mo. Dedicated Desk at the GoLab"}], "hackathon-location-google-maps": "https://maps.google.com/?q=621 East 6th Street, Austin, TX 78702, USA", "hackathon-url": "https://hackingeast.devpost.com/", "hackathon-judging-criteria": [{"judging-criterion": "Should be extremely easy to use for non-tech savvy artists and fans."}, {"judging-criterion": "Extra points and consideration for all submissions that make use of a cross-device platform such as Apache Cordova (\n)"}, {"judging-criterion": "Submissions should all follow the app guidelines and make use of sample data and provided API's."}], "hackathon-location-address": "621 East 6th Street, Austin, TX 78702, USA", "hackathon-description-header": "The goal of this hackathon is to create a mobile app that helps local artists list their works, and people more effectively share the works with their network of art-appreciating friends and family.", "hackathon-prizes-total": "$5,610", "hackathon-location-description": "", "hackathon-end-date": "2014-03-21", "has-projects": "True"}