{"hackathon-description-text": "\nFull Hackathon Information via\u00a0", "hackathon-number-of-prizes": "1", "hackathon-id": "finclusion", "hackathon-judges": [{"judge-role": "", "judge-name": "Nikhil Panchal"}, {"judge-role": "", "judge-name": "D.K Smith"}, {"judge-role": "", "judge-name": "Erika Alter"}, {"judge-role": "", "judge-name": "Peter Liu"}], "hackathon-number-of-judges": "4", "hackathon-eligibility": "", "hackathon-number-of-participants": "16", "hackathon-is-colocated": "True", "hackathon-has-ended": "False", "hackathon-number-of-judging-criteria": "6", "hackathon-requirements": "", "hackathon-rules": "\nCountries: United States only\u00a0", "hackathon-prizes": [{"prize-content": "", "prize-title": "Google Home"}], "hackathon-location-google-maps": "https://maps.google.com/?q=394 Broadway, New York, NY 10013, USA", "hackathon-url": "https://finclusion.devpost.com/", "hackathon-judging-criteria": [{"judging-criterion": "From a financial perspective. What impact does your idea have on the users of your product?"}, {"judging-criterion": "How confident are you that users will use your product?"}, {"judging-criterion": "Is your product easy to use and understand?"}, {"judging-criterion": "How is your product unique?"}, {"judging-criterion": "The complexity of the technology used."}, {"judging-criterion": "The potential in which you think your business will grow exponentially."}], "hackathon-location-address": "394 Broadway, New York, NY 10013, USA", "hackathon-description-header": "FinClusion hackathon bringing together individuals to make fintech more inclusive.", "hackathon-prizes-total": "0", "hackathon-location-description": "Impact Hub NYC", "hackathon-end-date": "", "has-projects": "False"}