{"hackathon-description-text": "\n\u00a0", "hackathon-number-of-prizes": "1", "hackathon-id": "un-women-refugees-1", "hackathon-judges": [{"judge-role": "UN Women", "judge-name": "Caroline Rusten"}, {"judge-role": "UN Women", "judge-name": "Soren Thomassen"}, {"judge-role": "Innovation Norway", "judge-name": "Paal Naess"}, {"judge-role": "ConsenSys", "judge-name": "Saraswathi Subbaraman"}, {"judge-role": "ConsenSys", "judge-name": "Jordan Leigh"}, {"judge-role": "United Nations", "judge-name": "Yoshiyuki Yamamoto"}], "hackathon-number-of-judges": "6", "hackathon-eligibility": "", "hackathon-number-of-participants": "24", "hackathon-is-colocated": "True", "hackathon-has-ended": "True", "hackathon-number-of-judging-criteria": "4", "hackathon-requirements": "\nSubmit your project and team on this DevPost by Thursday at 16:30.", "hackathon-rules": "\nNeed to rehearse your presenation between 13:00 - 15:00 on Thursday.\nPresentations will be five minutes in length with up to 3 minutes of judges questions. (length of presenation may change)", "hackathon-prizes": [{"prize-content": "", "prize-title": "Present at Katapult on Friday May 12, 2017"}], "hackathon-location-google-maps": "https://maps.google.com/?q=M\u00f8lleparken 4, 0459 Oslo, Norway", "hackathon-url": "https://un-women-refugees-1.devpost.com/", "hackathon-judging-criteria": [{"judging-criterion": ""}, {"judging-criterion": ""}, {"judging-criterion": ""}, {"judging-criterion": ""}], "hackathon-location-address": "M\u00f8lleparken 4, 0459 Oslo, Norway", "hackathon-description-header": "Blockchain tech in humanitarian work at Katapult Future Fest, Oslo, Norway", "hackathon-prizes-total": "0", "hackathon-location-description": "Katapult Future Fest", "hackathon-end-date": "2017-05-11", "has-projects": "True"}