{"hackathon-description-text": "\n2:30 PM - Registro", "hackathon-number-of-prizes": "1", "hackathon-id": "socialhack", "hackathon-judges": [{"judge-role": "", "judge-name": "Anah\u00ed Flores"}], "hackathon-number-of-judges": "1", "hackathon-eligibility": "", "hackathon-number-of-participants": "6", "hackathon-is-colocated": "True", "hackathon-has-ended": "False", "hackathon-number-of-judging-criteria": "3", "hackathon-requirements": "", "hackathon-rules": "\nSe respetuoso, el acoso y el abuso nunca son tolerados. Si te encuentras en una situaci\u00f3n que te hace sentir incomodo, o bien, el evento esta creando un ambiente peligroso y/o inapropiado, o un representante u organizador te hace sentir incomodo, por favor reportarlo utilizando los los procedimientos incluidos en este documento.\nNos comprometemos a la inclusi\u00f3n. Creemos que cada persona tiene el derecho de participar en un ambiente c\u00f3modo y seguro.\nEl acoso incluye, pero no esta limitado a: ofensas verbales o comentarios escritos relacionados con genero, edad, orientaci\u00f3n sexual, discapacidad, apariencia f\u00edsica, cuerpo, raza, religi\u00f3n, contenido pornogr\u00e1fico en \u00e1reas publicas, intimidaci\u00f3n intencionada, seguir fisicamente, fotograf\u00edas, grabar, interrumpir seguida e intencionalmente el dialogo de otros, contacto f\u00edsico inapropiado y/o llamar la atenci\u00f3n sexualmente.\nSi lo estas incurriendo en un acto que provoca incomodidad en otras personas, eso cuenta como acoso y es suficiente justificaci\u00f3n para dejar de hacerlo.\nLos participantes a los que se les indique abstener cualquier comportamiento considerado como acoso, deber\u00e1n cumplir con las indicaciones de manera inmediata.\nTodos los patrocinadores, jueces, mentores, voluntarios, organizadores y todos los dem\u00e1s participes del evento tambi\u00e9n son sujetos a est\u00e1s pol\u00edticas contra el acoso. En particular, los participantes no deber\u00e1n utilizar im\u00e1genes, actividades u otro material de contenido sexual en ambos su proyecto y durante el evento.\nLos colaboradores (incluidos voluntarios) no deber\u00e1n usar ninguna prenda, uniforme, disfraz cuyo contenido sea de materia sexual, o bien, crear un ambiente de materia sexual.\nSi un participante da lugar a un comportamiento de acoso, la administraci\u00f3n tomar\u00e1 cualquier acci\u00f3n que vea apropiada, incluyendo pero no limitado a advertir al ofensor, la expulsi\u00f3n del mismo del evento sin oportunidad de reembolso o reintegraci\u00f3n de cualquier tipo.\nSi te sientes acosado, notas que alguien esta siendo acosado o tienes cualquier otra preocupaci\u00f3n, por favor contactanos usando los procedimientos definidos a continuaci\u00f3n.\nNuestros representantes estar\u00e1n dispuestos a ayudar a todos los participantes y a contactar la seguridad del campus, o bien, fuerzas legales, proveer escoltas o bien, asistir a aquellos afectados por un acto de acoso para sentirse seguro durante el resto del evento. Valoramos mucho tu participaci\u00f3n.\nProcedimiento para reportar situaciones de acoso.\n Si te sientes incomodo o crees que pueda haber una violaci\u00f3n a este c\u00f3digo de conducta, por favor haznos saber utilizando alguno de los m\u00e9todos siguientes. Todo aquel que reporte tiene el derecho a anonimato.\n\u00a0", "hackathon-prizes": [{"prize-content": "", "prize-title": "INC MTY"}], "hackathon-location-google-maps": "https://maps.google.com/?q=Eugenio Garza Sada 2501, Las Brisas, Monterrey, N.L., Mexico", "hackathon-url": "https://socialhack.devpost.com/", "hackathon-judging-criteria": [{"judging-criterion": ""}, {"judging-criterion": ""}, {"judging-criterion": ""}], "hackathon-location-address": "Eugenio Garza Sada 2501, Las Brisas, Monterrey, N.L., Mexico", "hackathon-description-header": "Soluciones que cambien la vida de 1 mill\u00f3n de personas en temas de impacto social, desastres naturales y medio ambiente.", "hackathon-prizes-total": "$3,000", "hackathon-location-description": "Tec de Monterrey - Innovaction Gym", "hackathon-end-date": "", "has-projects": "False"}