{"hackathon-description-text": "\nEs el acontecimiento m\u00e1s importante para la comunidad tecnol\u00f3gica de Durango, donde expertos se re\u00fanen para intercambiar experiencias y compartir lo m\u00e1s nuevo en el mundo de Internet.", "hackathon-number-of-prizes": "5", "hackathon-id": "virtuafest", "hackathon-judges": [{"judge-role": "Major League Hacking", "judge-name": "Juan Pablo Flores Cort\u00e9s"}], "hackathon-number-of-judges": "1", "hackathon-eligibility": "\nSolamente aceptaremos proyectos que se desarrollen durante el evento y los participantes deben de presentrase en el evento.", "hackathon-number-of-participants": "27", "hackathon-is-colocated": "True", "hackathon-has-ended": "True", "hackathon-number-of-judging-criteria": "4", "hackathon-requirements": "\nEsperamos un MVP de tu desarrollo.\u00a0", "hackathon-rules": "\nCodigo de Conducta de la MLH", "hackathon-prizes": [{"prize-content": "", "prize-title": "Dell Venue 7 Tablets de Major League Hacking"}, {"prize-content": "", "prize-title": "Smart Watch patrocinadas por el gobierno municipal"}, {"prize-content": "", "prize-title": "Lap Top HP patrocinada por Virtua"}, {"prize-content": "", "prize-title": "Medallas Finalista"}, {"prize-content": "", "prize-title": "Audifonos Skull Candy patrocinadas por Idea de Gentera"}], "hackathon-location-google-maps": "https://maps.google.com/?q=Del Parque, Durango, Dgo., Mexico", "hackathon-url": "https://virtuafest.devpost.com/", "hackathon-judging-criteria": [{"judging-criterion": "Que tan visualmente atractiva es la aplicacion."}, {"judging-criterion": "Es sencilla de utilizar"}, {"judging-criterion": "Que tan complejo es el c\u00f3digo de tu proyecto"}, {"judging-criterion": "Que tan fuera de lo convencional es tu proyecto"}], "hackathon-location-address": "Del Parque, Durango, Dgo., Mexico", "hackathon-description-header": "El primer hackaton para estudiantes en Durango", "hackathon-prizes-total": "0", "hackathon-location-description": "Bebeleche Museum", "hackathon-end-date": "2015-10-24", "has-projects": "True"}