{"hackathon-description-text": "\ntry! Swift is an immersive community gathering about Swift Language Best Practices, Application Development in Swift, Server-Side Swift, Open Source Swift, and the Swift Community. It will take place in Tokyo with talks from community experts on March 2nd and 3rd, and a Swift hackathon on March 4th.\u00a0", "hackathon-number-of-prizes": "4", "hackathon-id": "tryswift", "hackathon-judges": [{"judge-role": "@masuidrive", "judge-name": "Yuichiro Masui"}, {"judge-role": "@shu223", "judge-name": "Shuichi Tsutsumi"}, {"judge-role": "@inamiy", "judge-name": "Yasuhiro Inami"}, {"judge-role": "", "judge-name": "Kazuaki Matsuo"}, {"judge-role": "", "judge-name": "Rikke M\u00f8ller Koblauch"}, {"judge-role": "", "judge-name": "Orta Therox"}, {"judge-role": "", "judge-name": "Agnes Vasarhelyi"}, {"judge-role": "", "judge-name": "Jon Reid"}, {"judge-role": "", "judge-name": "Laura Ragone"}, {"judge-role": "", "judge-name": "Himi Sato"}, {"judge-role": "", "judge-name": "Mo Kudeki"}, {"judge-role": "", "judge-name": "Sommer Panage"}, {"judge-role": "", "judge-name": "Christopher Rogers"}, {"judge-role": "", "judge-name": "Krzysztof Siejkowski"}, {"judge-role": "", "judge-name": "Soroush Khanlou"}, {"judge-role": "", "judge-name": "Kyle Fuller"}, {"judge-role": "", "judge-name": "Meghan Kane"}, {"judge-role": "", "judge-name": "Alexis Gallagher"}, {"judge-role": "", "judge-name": "Ray Fix"}, {"judge-role": "", "judge-name": "Ray Tsaihong"}, {"judge-role": "", "judge-name": "Shinichi Goto"}, {"judge-role": "", "judge-name": "Derek Lee"}, {"judge-role": "", "judge-name": "Seiyo Kurita (niwatako)"}], "hackathon-number-of-judges": "23", "hackathon-eligibility": "", "hackathon-number-of-participants": "203", "hackathon-is-colocated": "True", "hackathon-has-ended": "True", "hackathon-number-of-judging-criteria": "2", "hackathon-requirements": "", "hackathon-rules": "\nYou are strongly encouraged to form teams and ideas \n the hackathon day. Those who do not form teams, will only have a short 45 minutes to do so during the hackathon day. Teams should be a maximum of 6 people - a team of 1 is ok if you'd rather work on your own.\u00a0\n\u30cf\u30c3\u30ab\u30bd\u30f3\u958b\u50ac\u65e5\u306e\u524d\u306b\u30c1\u30fc\u30e0\u7de8\u6210\u3068\u30a2\u30a4\u30c7\u30a2\u51fa\u3057\u3092\u884c\u3063\u3066\u304a\u304f\u3053\u3068\u3092\u5f37\u304f\u304a\u52e7\u3081\u3057\u307e\u3059\u3002 \u30c1\u30fc\u30e0\u3092\u7d44\u3093\u3067\u3044\u306a\u3044\u4eba\u306f\u3001\u30cf\u30c3\u30ab\u30bd\u30f3\u958b\u50ac\u65e5\u306b\u30c1\u30fc\u30e0\u7de8\u6210\u306e\u305f\u3081\u306e\u6642\u9593\u304c45\u5206\u3057\u304b\u3042\u308a\u307e\u305b\u3093\u3002\u30c1\u30fc\u30e0\u306f\u6700\u59276\u540d\u3067\u3059\u3002\u3082\u30571\u4eba\u3067\u4f5c\u696d\u3057\u305f\u3044\u5834\u5408\u306f\u30011\u4eba\u306e\u30c1\u30fc\u30e0\u3067\u3082OK\u3067\u3059\u3002\u00a0\nIf you don't already have a team, post a \n\u00a0on devpost, in the Discussions tab. Discuss your idea, and see if others will join your team. You can also \n\u00a0to check if they are interested in joining your team.\u00a0\n\u3042\u306a\u305f\u304c\u307e\u3060\u30c1\u30fc\u30e0\u306b\u5165\u3063\u3066\u3044\u306a\u3044\u5834\u5408\u306f\u3001devpost\u306e\u300c\u30c7\u30a3\u30b9\u30ab\u30c3\u30b7\u30e7\u30f3\u300d\u30bf\u30d6\u306b\u65b0\u3057\u3044\u30c7\u30a3\u30b9\u30ab\u30c3\u30b7\u30e7\u30f3\u30c8\u30d4\u30c3\u30af\u3092\u6295\u7a3f\u3057\u3066\u304f\u3060\u3055\u3044\u3002 \u3042\u306a\u305f\u306e\u30a2\u30a4\u30c7\u30a2\u306b\u3064\u3044\u3066\u8a71\u3057\u5408\u3044\u3001\u4ed6\u306e\u4eba\u304c\u3042\u306a\u305f\u306e\u30c1\u30fc\u30e0\u306b\u52a0\u308f\u308b\u304b\u3069\u3046\u304b\u3092\u898b\u3066\u304f\u3060\u3055\u3044\u3002 \u4ed6\u306e\u30cf\u30c3\u30ab\u30bd\u30f3\u53c2\u52a0\u8005\u306b\u5bfe\u3057\u3066\u3001\u3042\u306a\u305f\u306e\u30c1\u30fc\u30e0\u3078\u306e\u53c2\u52a0\u306b\u8208\u5473\u304c\u3042\u308b\u304b\u3069\u3046\u304b\u3092\u78ba\u8a8d\u3059\u308b\u30e1\u30c3\u30bb\u30fc\u30b8\u3092\u9001\u308b\u3053\u3068\u3082\u3067\u304d\u307e\u3059\u3002\nThe theme of the hackathon is \n. It is very open-ended for a reason - we want to see your creativity and innovation with Swift! That said, the main purpose of the hackathon is to learn something new. Maybe there was something you wanted to try with Swift or iOS SDK, but haven't had a chance to yet. This is your day to try that new technology! Build tools, frameworks, websites, Android Apps, iOS Apps, contribute to open-source Swift, write scripts, anything as long as it's using Swift!\n\u30cf\u30c3\u30ab\u30bd\u30f3\u306e\u30c6\u30fc\u30de\u306f\u3001\u300cSwift\u3067\u30a4\u30ce\u30d9\u30fc\u30b7\u30e7\u30f3\u3092\u8d77\u3053\u305d\u3046\uff01\u300d\u3067\u3059\u3002 \u79c1\u305f\u3061\u306f\u307f\u306a\u3055\u3093\u306eSwift\u306b\u3088\u308b\u30af\u30ea\u30a8\u30a4\u30c6\u30a3\u30d3\u30c6\u30a3\u3068\u30a4\u30ce\u30d9\u30fc\u30b7\u30e7\u30f3\u3092\u898b\u305f\u3044\u3067\u3059\uff01\u3053\u306e\u30cf\u30c3\u30ab\u30bd\u30f3\u306e\u4e3b\u306a\u76ee\u7684\u306f\u3001\u4f55\u304b\u65b0\u3057\u3044\u3053\u3068\u3092\u5b66\u3076\u3053\u3068\u3067\u3059\u3002 \u304a\u305d\u3089\u304f\u3001\u4eca\u307e\u3067\u30c1\u30e3\u30f3\u30b9\u304c\u306a\u304f\u3066\u3001Swift\u3084iOS SDK\u3067\u8a66\u3057\u3066\u307f\u305f\u3044\u3053\u3068\u304c\u3042\u308b\u3068\u601d\u3044\u307e\u3059\u3002\u5f53\u65e5\u306f\u3001\u3042\u306a\u305f\u304c\u53d6\u308a\u7d44\u3081\u306a\u304b\u3063\u305f\u65b0\u3057\u3044\u6280\u8853\u306b\u6311\u6226\u3059\u308b1\u65e5\u3067\u3059\uff01Swift\u3092\u4f7f\u7528\u3057\u3066\u3044\u308c\u3070\u3001\u30d3\u30eb\u30c9\u30c4\u30fc\u30eb\u30fb\u30d5\u30ec\u30fc\u30e0\u30ef\u30fc\u30af\u30fb\u30a6\u30a7\u30d6\u30b5\u30a4\u30c8\u30fbAndroid\u30a2\u30d7\u30ea\u30fbiOS\u30a2\u30d7\u30ea\u30fb\u30aa\u30fc\u30d7\u30f3\u30bd\u30fc\u30b9Swift\u3078\u306e\u8ca2\u732e\u30fb\u30b9\u30af\u30ea\u30d7\u30c8\u306e\u4f5c\u6210\u306a\u3069\u306b\u53d6\u308a\u7d44\u3080\u3053\u3068\u304c\u53ef\u80fd\u3067\u3059\u3002\nOnce you have your idea, create a \n. You can modify the submission (including adding new team members) up until the hackathon coding ends at 18:00 on March 4th. It is better to create it earlier (even before the hackathon) so you don't have to worry about it during the hackthon.\n\u3044\u3063\u305f\u3093\u3042\u306a\u305f\u306e\u30a2\u30a4\u30c7\u30a3\u30a2\u304c\u3067\u304d\u305f\u3089\u3001\u300cnew hackathon submission\u300d\u3092\u4f5c\u6210\u3057\u3066\u4e0b\u3055\u3044\u30023\u67084\u65e5\u306e18:00\u306b\u30cf\u30c3\u30ab\u30bd\u30f3\u3067\u306e\u30b3\u30fc\u30c7\u30a3\u30f3\u30b0\u304c\u7d42\u4e86\u3059\u308b\u307e\u3067\u3001\u63d0\u51fa\u5185\u5bb9\u3092\u5909\u66f4\u3059\u308b\u3053\u3068\u304c\u3067\u304d\u307e\u3059\uff08\u65b0\u3057\u3044\u30c1\u30fc\u30e0\u30e1\u30f3\u30d0\u30fc\u306e\u8ffd\u52a0\u3092\u542b\u307f\u307e\u3059\uff09\u3002\u30cf\u30c3\u30ab\u30bd\u30f3\u306e\u958b\u50ac\u4e2d\u306b\u305d\u308c\u306b\u3064\u3044\u3066\u5fc3\u914d\u3059\u308b\u5fc5\u8981\u304c\u306a\u3044\u3088\u3046\u306b\u3001\uff08\u30cf\u30c3\u30ab\u30bd\u30f3\u306e\u524d\u3067\u3042\u3063\u3066\u3082\uff09\u305d\u308c\u3092\u65e9\u304f\u4f5c\u6210\u3059\u308b\u307b\u3046\u304c\u826f\u3044\u3067\u3057\u3087\u3046\u3002\nThe judges will use your devpost submission to select winners. There will be 3 different rounds of judging. Only 10 teams will be selected to present their project to everyone in the final judging round on March 4th.\u00a0\n\u5be9\u67fb\u54e1\u306f\u3042\u306a\u305f\u306edevpost\u3078\u306e\u6295\u7a3f\u3092\u4f7f\u7528\u3057\u3066\u52dd\u8005\u3092\u9078\u629e\u3057\u307e\u3059\u3002 3\u56de\u306e\u5be9\u67fb\u304c\u884c\u308f\u308c\u307e\u3059\u3002 3\u67084\u65e5\u306e\u6700\u7d42\u5be9\u67fb\u306b\u304a\u3044\u3066\u767b\u58c7\u3057\u3066\u5168\u54e1\u306e\u524d\u3067\u30d7\u30ed\u30b8\u30a7\u30af\u30c8\u306e\u6210\u679c\u3092\u767a\u8868\u3067\u304d\u308b\u30c1\u30fc\u30e0\u306f10\u30c1\u30fc\u30e0\u3060\u3051\u3067\u3059\u3002\n\u00a0", "hackathon-prizes": [{"prize-content": "", "prize-title": "Nintendo Switch"}, {"prize-content": "", "prize-title": "AirPods"}, {"prize-content": "", "prize-title": "Drone"}, {"prize-content": "", "prize-title": "Star Wars Millennium Falcon LEGO"}], "hackathon-location-google-maps": "", "hackathon-url": "https://tryswift.devpost.com/", "hackathon-judging-criteria": [{"judging-criterion": "The code must be written in Swift. / \u30b3\u30fc\u30c9\u306f\u5fc5\u305aSwift\u3067\u66f8\u3044\u3066\u304f\u3060\u3055\u3044\u3002"}, {"judging-criterion": "The maximum number of participants on a team should be six. / 1\u30c1\u30fc\u30e0\u6700\u59276\u540d\u3067\u3059\u3002"}], "hackathon-location-address": "", "hackathon-description-header": "try! Swift Tokyo 2017", "hackathon-prizes-total": "$650", "hackathon-location-description": "BELLESALLE Kanda", "hackathon-end-date": "2017-03-04", "has-projects": "True"}