{"hackathon-description-text": "\nIt's time to set Kansas City's gigabit network ablaze!\u00a0Join us for a weekend of", "hackathon-number-of-prizes": "1", "hackathon-id": "gighacks-kc", "hackathon-judges": [{"judge-role": "", "judge-name": "Will be Announced"}], "hackathon-number-of-judges": "1", "hackathon-eligibility": "\nDevelopers, designers, dreamers & doers who want to advance their applications with gigabit networks\n\u00a0", "hackathon-number-of-participants": "41", "hackathon-is-colocated": "True", "hackathon-has-ended": "False", "hackathon-number-of-judging-criteria": "1", "hackathon-requirements": "\nFeatures of gigabit:", "hackathon-rules": "\nRules will be updated later on.", "hackathon-prizes": [{"prize-content": "", "prize-title": "Will be Announced"}], "hackathon-location-google-maps": "https://maps.google.com/?q=1814 Westport Road, Kansas City, MO 64111, USA", "hackathon-url": "https://gighacks-kc.devpost.com/", "hackathon-judging-criteria": [{"judging-criterion": ""}], "hackathon-location-address": "1814 Westport Road, Kansas City, MO 64111, USA", "hackathon-description-header": "A 3-day hack event to ignite the gigabit experience.", "hackathon-prizes-total": "0", "hackathon-location-description": "", "hackathon-end-date": "", "has-projects": "False"}