{"participant-likes": "1", "participant-projects": "1", "participant-url": "https://devpost.com/__ml__", "participant-name": "Michael L", "participant-followers": "3", "participant-location": "Munich, Bavaria, Germany", "participant-bio": "", "participant-id": "__ml__", "participant-linkedin": "", "participant-website": "", "participant-github": "", "participant-hackathons": "1", "participant-following": "1", "participant-number-of-skills": "0", "participant-skills": [], "participant-twitter": ""}