{"hackathon-winner": "False", "project-technologies-used": "4", "project-video": "https://www.youtube.com/embed/LRMrBaNkLVc?enablejsapi=1&hl=en_US&rel=0&version=3&wmode=transparent", "project-basis": "", "project-technologies": [{"url": "", "name": "pc-itx-motherboard"}, {"url": "https://devpost.com/software/built-with/c", "name": "c"}, {"url": "https://devpost.com/software/built-with/linux", "name": "linux"}, {"url": "", "name": "http://www.linphone.org/"}], "project-challenges": "I  write a SIP Server", "project-future-plans": "Show SeeMe to all parson", "project-purpose": "", "hackathon-url": "", "project-title": "SeeMe", "project-inspiration": "We wanted to find a low cost solution to\nprovide quality videoconferencing (synchronous voice and video) to a very large number of\nusers. The control is made in Phone number 218133503 and the Robot is in 219592517", "project-lessons-learned": "That work, the WAN of circuit with IP is real", "project-accomplishments": "Control the", "project-likes": "0", "hackathon-name": "", "project-subtitle": "Telerobotics Videoconference", "project-github-url": "", "project-number-of-comments": "0", "team-size": "1", "project-creation-timestamp": "2015-05-26T16:57:24-04:00", "team": [{"participant-bubble": "", "participant-name": "", "participant-desc": "", "participant-url": ""}], "project-url": "https://devpost.com/software/seeme", "project-id": "34487"}