{"hackathon-winner": "False", "project-technologies-used": "1", "project-video": "https://www.youtube.com/embed/ZLVmCDBf4PI?enablejsapi=1&hl=en_US&rel=0&version=3&wmode=transparent", "project-basis": "", "project-technologies": [{"url": "https://devpost.com/software/built-with/hardware", "name": "hardware"}], "project-challenges": "", "project-future-plans": "", "project-purpose": "", "hackathon-url": "https://gearapp.devpost.com/", "project-title": "Dark Simple Clock", "project-inspiration": "", "project-lessons-learned": "", "project-accomplishments": "", "project-likes": "0", "hackathon-name": "Samsung Gear App Challenge", "project-subtitle": "When you need to suit up, suit up your gear as well as your clothes", "project-github-url": "", "project-number-of-comments": "0", "team-size": "1", "project-creation-timestamp": "2014-07-17T17:22:21-04:00", "team": [{"participant-bubble": "", "participant-name": "", "participant-desc": "", "participant-url": ""}], "project-url": "https://devpost.com/software/dark-simple-clock--2", "project-id": "13384"}