{"hackathon-winner": "False", "project-technologies-used": "8", "project-video": "", "project-basis": "", "project-technologies": [{"url": "https://devpost.com/software/built-with/node-js", "name": "node.js"}, {"url": "https://devpost.com/software/built-with/express-js", "name": "express.js"}, {"url": "https://devpost.com/software/built-with/socket-io", "name": "socket.io"}, {"url": "https://devpost.com/software/built-with/knockout-js", "name": "knockout.js"}, {"url": "https://devpost.com/software/built-with/underscorejs", "name": "underscorejs"}, {"url": "https://devpost.com/software/built-with/coffeescript", "name": "coffeescript"}, {"url": "https://devpost.com/software/built-with/grunt-js", "name": "grunt.js"}, {"url": "https://devpost.com/software/built-with/web", "name": "web"}], "project-challenges": "", "project-future-plans": "", "project-purpose": "", "hackathon-url": "https://mhackswinter2014.devpost.com/", "project-title": "Duet", "project-inspiration": "", "project-lessons-learned": "", "project-accomplishments": "", "project-likes": "0", "hackathon-name": "MHacks Winter 2014", "project-subtitle": "", "project-github-url": "", "project-number-of-comments": "0", "team-size": "1", "project-creation-timestamp": "2014-03-21T17:59:20-04:00", "team": [{"participant-bubble": "", "participant-name": "", "participant-desc": "", "participant-url": ""}], "project-url": "https://devpost.com/software/duet", "project-id": "5342"}