{"hackathon-winner": "False", "project-technologies-used": "2", "project-video": "https://www.youtube.com/embed/HcLY_GX_aKo?enablejsapi=1&hl=en_US&rel=0&version=3&wmode=transparent", "project-basis": "", "project-technologies": [{"url": "", "name": "sms"}, {"url": "https://devpost.com/software/built-with/google-maps", "name": "google-maps"}], "project-challenges": "", "project-future-plans": "", "project-purpose": "", "hackathon-url": "https://datafordiplomas.devpost.com/", "project-title": "American Graduates", "project-inspiration": "To tackle effects of low graduation rates for every School Districts in every states in United States,\nI started by making a json Call to USA Census Dataset files and import it to database.", "project-lessons-learned": "", "project-accomplishments": "", "project-likes": "0", "hackathon-name": "AT&T Data for Diplomas", "project-subtitle": "An app that analyze, Predicts and Boasts American Students Graduation Rates by 99.99%", "project-github-url": "", "project-number-of-comments": "0", "team-size": "1", "project-creation-timestamp": "2015-11-16T14:57:05-05:00", "team": [{"participant-bubble": "", "participant-name": "", "participant-desc": "", "participant-url": ""}], "project-url": "https://devpost.com/software/american-graduates", "project-id": "46875"}