{"hackathon-winner": "False", "project-technologies-used": "4", "project-video": "", "project-basis": "", "project-technologies": [{"url": "https://devpost.com/software/built-with/html", "name": "html"}, {"url": "https://devpost.com/software/built-with/css", "name": "css"}, {"url": "https://devpost.com/software/built-with/javascript", "name": "javascript"}, {"url": "https://devpost.com/software/built-with/php", "name": "php"}], "project-challenges": "", "project-future-plans": "", "project-purpose": "", "hackathon-url": "https://broncohack2017.devpost.com/", "project-title": "BroncoHack17", "project-inspiration": "", "project-lessons-learned": "", "project-accomplishments": "", "project-likes": "0", "hackathon-name": "BroncoHack 2017", "project-subtitle": "A crowdfunding service for K-12 public schools in poverty areas", "project-github-url": "https://github.com/yueqisuuuuu/BroncoHack17", "project-number-of-comments": "0", "team-size": "1", "project-creation-timestamp": "2017-04-15T14:57:06-04:00", "team": [{"participant-bubble": "", "participant-name": "", "participant-desc": "", "participant-url": ""}], "project-url": "https://devpost.com/software/broncohack17", "project-id": "90697"}