{"hackathon-winner": "False", "project-technologies-used": "4", "project-video": "", "project-basis": "", "project-technologies": [{"url": "", "name": "touch-develop"}, {"url": "https://devpost.com/software/built-with/web", "name": "web"}, {"url": "https://devpost.com/software/built-with/windows", "name": "windows"}, {"url": "https://devpost.com/software/built-with/windows-phone", "name": "windows-phone"}], "project-challenges": "", "project-future-plans": "", "project-purpose": "", "hackathon-url": "https://hshacks.devpost.com/", "project-title": "College Loan Calculator", "project-inspiration": "", "project-lessons-learned": "", "project-accomplishments": "", "project-likes": "0", "hackathon-name": "HSHacks", "project-subtitle": "", "project-github-url": "", "project-number-of-comments": "0", "team-size": "1", "project-creation-timestamp": "2014-03-21T18:12:40-04:00", "team": [{"participant-bubble": "", "participant-name": "", "participant-desc": "", "participant-url": ""}], "project-url": "https://devpost.com/software/college-loan-calculator", "project-id": "7234"}