{"hackathon-winner": "False", "project-technologies-used": "7", "project-video": "https://www.youtube.com/embed/n4MNmIXpFhw?enablejsapi=1&hl=en_US&rel=0&version=3&wmode=transparent", "project-basis": "", "project-technologies": [{"url": "https://devpost.com/software/built-with/html", "name": "html"}, {"url": "https://devpost.com/software/built-with/css", "name": "css"}, {"url": "https://devpost.com/software/built-with/javascript", "name": "javascript"}, {"url": "https://devpost.com/software/built-with/hardware", "name": "hardware"}, {"url": "https://devpost.com/software/built-with/mac", "name": "mac"}, {"url": "https://devpost.com/software/built-with/web", "name": "web"}, {"url": "https://devpost.com/software/built-with/windows", "name": "windows"}], "project-challenges": "", "project-future-plans": "", "project-purpose": "", "hackathon-url": "", "project-title": "Gear Call screen", "project-inspiration": "", "project-lessons-learned": "", "project-accomplishments": "", "project-likes": "0", "hackathon-name": "", "project-subtitle": "Gear App Challenge", "project-github-url": "http://htmlpreview.github.io/?https://github.com/mohanraj0411/gear/blob/gh-pages/index.html", "project-number-of-comments": "0", "team-size": "1", "project-creation-timestamp": "2014-06-26T14:25:09-04:00", "team": [{"participant-bubble": "", "participant-name": "", "participant-desc": "", "participant-url": ""}], "project-url": "https://devpost.com/software/gear-call-screen", "project-id": "12514"}