{"hackathon-winner": "False", "project-technologies-used": "5", "project-video": "", "project-basis": "", "project-technologies": [{"url": "https://devpost.com/software/built-with/python", "name": "python"}, {"url": "https://devpost.com/software/built-with/django", "name": "django"}, {"url": "https://devpost.com/software/built-with/css3", "name": "css3"}, {"url": "https://devpost.com/software/built-with/html5", "name": "html5"}, {"url": "", "name": "kedfilms"}], "project-challenges": "", "project-future-plans": "", "project-purpose": "", "hackathon-url": "", "project-title": "Personal Website", "project-inspiration": "", "project-lessons-learned": "", "project-accomplishments": "", "project-likes": "0", "hackathon-name": "", "project-subtitle": "Stylish Django Website w/o Javascript", "project-github-url": "https://github.com/sevaivanov/personal-website", "project-number-of-comments": "0", "team-size": "1", "project-creation-timestamp": "2015-08-20T00:23:29-04:00", "team": [{"participant-bubble": "Full-stack", "participant-name": "", "participant-desc": "", "participant-url": ""}], "project-url": "https://devpost.com/software/kedfilms-com", "project-id": "37832"}