{"hackathon-winner": "False", "project-technologies-used": "1", "project-video": "", "project-basis": "", "project-technologies": [{"url": "https://devpost.com/software/built-with/java", "name": "java"}], "project-challenges": "", "project-future-plans": "", "project-purpose": "", "hackathon-url": "", "project-title": "BeamForge", "project-inspiration": "", "project-lessons-learned": "", "project-accomplishments": "", "project-likes": "0", "hackathon-name": "", "project-subtitle": "CNC Software for Hackerspaces", "project-github-url": "", "project-number-of-comments": "0", "team-size": "1", "project-creation-timestamp": "2016-05-03T11:38:17-04:00", "team": [{"participant-bubble": "", "participant-name": "", "participant-desc": "", "participant-url": ""}], "project-url": "https://devpost.com/software/beamforge", "project-id": "61433"}