{"hackathon-winner": "False", "project-technologies-used": "15", "project-video": "", "project-basis": "", "project-technologies": [{"url": "https://devpost.com/software/built-with/eclipse", "name": "eclipse"}, {"url": "https://devpost.com/software/built-with/html5", "name": "html5"}, {"url": "https://devpost.com/software/built-with/css3", "name": "css3"}, {"url": "https://devpost.com/software/built-with/javascript", "name": "javascript"}, {"url": "https://devpost.com/software/built-with/jquery", "name": "jquery"}, {"url": "https://devpost.com/software/built-with/java", "name": "java"}, {"url": "", "name": "sparc"}, {"url": "https://devpost.com/software/built-with/maven", "name": "maven"}, {"url": "https://devpost.com/software/built-with/notepad", "name": "notepad++"}, {"url": "", "name": "server"}, {"url": "https://devpost.com/software/built-with/bash", "name": "bash"}, {"url": "", "name": "virtual-box"}, {"url": "https://devpost.com/software/built-with/gimp", "name": "gimp"}, {"url": "https://devpost.com/software/built-with/mspaint", "name": "mspaint"}, {"url": "https://devpost.com/software/built-with/chrome", "name": "chrome"}], "project-challenges": "", "project-future-plans": "", "project-purpose": "", "hackathon-url": "https://hackumass-ii.devpost.com/", "project-title": "SANSCHED", "project-inspiration": "", "project-lessons-learned": "", "project-accomplishments": "", "project-likes": "0", "hackathon-name": "HackUMass", "project-subtitle": "scheduling \"san\" hassle\"", "project-github-url": "", "project-number-of-comments": "0", "team-size": "1", "project-creation-timestamp": "2015-04-12T12:04:50-04:00", "team": [{"participant-bubble": "I worked primarily on the front end and planning stages. I worked on laying out the forms, background image and banner. I designed a theme for our pages. I focused on the CSS and HTML aspects", "participant-name": "", "participant-desc": "", "participant-url": ""}], "project-url": "https://devpost.com/software/sansched", "project-id": "31711"}