{"hackathon-winner": "False", "project-technologies-used": "5", "project-video": "", "project-basis": "I used meteor.js to make the mobile application views, and standard JavaScript to make the appropriate API calls.", "project-technologies": [{"url": "https://devpost.com/software/built-with/meteor-js", "name": "meteor.js"}, {"url": "https://devpost.com/software/built-with/html", "name": "html"}, {"url": "https://devpost.com/software/built-with/css", "name": "css"}, {"url": "https://devpost.com/software/built-with/git", "name": "git"}, {"url": "https://devpost.com/software/built-with/javascript", "name": "javascript"}], "project-challenges": "PayPal blocks you if you test too much, too close together.", "project-future-plans": "Posting on GitHub for others to use.", "project-purpose": "Automatically track who asked for what to be purchased, and when the items are purchased and the prices entered, the money is automatically withdrawn from the requestor's PayPal account.", "hackathon-url": "https://hackrpi2015.devpost.com/", "project-title": "grocerylist", "project-inspiration": "Friends hate going shopping for groceries, and hate hunting each other down to get paid back.", "project-lessons-learned": "", "project-accomplishments": "", "project-likes": "0", "hackathon-name": "HackRPI", "project-subtitle": "A platform to collaboratively build shopping lists and divide the cost amongst the participants.", "project-github-url": "https://github.com/drock371/the-grocery-runner", "project-number-of-comments": "0", "team-size": "1", "project-creation-timestamp": "2015-11-15T11:27:28-05:00", "team": [{"participant-bubble": "", "participant-name": "", "participant-desc": "", "participant-url": ""}], "project-url": "https://devpost.com/software/grocerylist", "project-id": "46760"}